tiny_voyageai/__init__.py
tiny_voyageai/cross_encoder.py
tiny_voyageai/embedder.py
tiny_voyageai/register.py
tinygent_voyageai-0.1.1007.dist-info/METADATA
tinygent_voyageai-0.1.1007.dist-info/WHEEL
tinygent_voyageai-0.1.1007.dist-info/entry_points.txt
tinygent_voyageai-0.1.1007.dist-info/RECORD
