Metadata-Version: 2.4
Name: tinygent-voyageai
Version: 0.1.1007
Requires-Dist: tinygent
Requires-Dist: voyageai>=0.3.7
